cpauto/__init__.py
cpauto/core/__init__.py
cpauto/core/exceptions.py
cpauto/core/misc.py
cpauto/core/sessions.py
cpauto/objects/__init__.py
cpauto/objects/_common.py
cpauto/objects/access.py
cpauto/objects/application.py
cpauto/objects/group.py
cpauto/objects/host.py
cpauto/objects/network.py
cpauto/objects/policy.py
cpauto/objects/service.py
cpauto/objects/simplegateway.py
cpauto/objects/threat.py
cpauto-0.0.5.dist-info/DESCRIPTION.rst
cpauto-0.0.5.dist-info/METADATA
cpauto-0.0.5.dist-info/RECORD
cpauto-0.0.5.dist-info/WHEEL
cpauto-0.0.5.dist-info/metadata.json
cpauto-0.0.5.dist-info/top_level.txt
