Metadata-Version: 2.0
Name: cpauto
Version: 0.0.5
Summary: Python client for Check Point R80 management server web APIs
Home-page: https://github.com/dana-at-cp/cpauto
Author: Dana James Traversie
Author-email: dtravers@checkpoint.com
License: Apache Software License
Platform: any
Classifier: Programming Language :: Python
Classifier: Programming Language :: Python :: 2.7
Classifier: Programming Language :: Python :: 3.5
Classifier: Development Status :: 4 - Beta
Classifier: Natural Language :: English
Classifier: Environment :: Web Environment
Classifier: Intended Audience :: Developers
Classifier: License :: OSI Approved :: Apache Software License
Classifier: Operating System :: OS Independent
Classifier: Topic :: Software Development :: Libraries :: Python Modules
Classifier: Topic :: Software Development :: Libraries :: Application Frameworks
Classifier: Topic :: Internet :: WWW/HTTP :: Dynamic Content
Requires-Dist: requests (>=2.11.1)
